smartsim/__init__.py
smartsim/experiment.py
smartsim/log.py
smartsim/py.typed
smartsim/servertype.py
smartsim/status.py
smartsim/version.py
smartsim/_core/__init__.py
smartsim/_core/types.py
smartsim/_core/_cli/__init__.py
smartsim/_core/_cli/__main__.py
smartsim/_core/_cli/build.py
smartsim/_core/_cli/clean.py
smartsim/_core/_cli/cli.py
smartsim/_core/_cli/dbcli.py
smartsim/_core/_cli/info.py
smartsim/_core/_cli/plugin.py
smartsim/_core/_cli/site.py
smartsim/_core/_cli/teardown.py
smartsim/_core/_cli/utils.py
smartsim/_core/_cli/validate.py
smartsim/_core/_cli/scripts/dragon_install.py
smartsim/_core/_install/__init__.py
smartsim/_core/_install/buildenv.py
smartsim/_core/_install/builder.py
smartsim/_core/_install/mlpackages.py
smartsim/_core/_install/platform.py
smartsim/_core/_install/redisaiBuilder.py
smartsim/_core/_install/types.py
smartsim/_core/_install/configs/mlpackages/DarwinARM64CPU.json
smartsim/_core/_install/configs/mlpackages/DarwinX64CPU.json
smartsim/_core/_install/configs/mlpackages/LinuxX64CPU.json
smartsim/_core/_install/configs/mlpackages/LinuxX64CUDA11.json
smartsim/_core/_install/configs/mlpackages/LinuxX64CUDA12.json
smartsim/_core/_install/configs/mlpackages/LinuxX64ROCM6.json
smartsim/_core/_install/utils/__init__.py
smartsim/_core/_install/utils/retrieve.py
smartsim/_core/config/__init__.py
smartsim/_core/config/config.py
smartsim/_core/config/keydb.conf
smartsim/_core/config/redis.conf
smartsim/_core/control/__init__.py
smartsim/_core/control/controller.py
smartsim/_core/control/controller_utils.py
smartsim/_core/control/job.py
smartsim/_core/control/jobmanager.py
smartsim/_core/control/manifest.py
smartsim/_core/control/previewrenderer.py
smartsim/_core/entrypoints/__init__.py
smartsim/_core/entrypoints/colocated.py
smartsim/_core/entrypoints/dragon.py
smartsim/_core/entrypoints/dragon_client.py
smartsim/_core/entrypoints/indirect.py
smartsim/_core/entrypoints/redis.py
smartsim/_core/entrypoints/telemetrymonitor.py
smartsim-0.8.0.dist-info/LICENSE.md
smartsim-0.8.0.dist-info/METADATA
smartsim-0.8.0.dist-info/WHEEL
smartsim-0.8.0.dist-info/entry_points.txt
smartsim-0.8.0.dist-info/top_level.txt
smartsim-0.8.0.dist-info/RECORD
