Metadata-Version: 2.1
Name: smartsim
Version: 0.8.0
Summary: AI Workflows for Science
Home-page: https://github.com/CrayLabs/SmartSim
Author: CrayLabs, a Hewlett Packard Enterprise OSS Organization
Author-email: craylabs@hpe.com
License: BSD 2-Clause License
Project-URL: Source, https://github.com/CrayLabs/SmartSim
Project-URL: Documentation, https://www.craylabs.org
Keywords: scientific,ai,workflow,hpc,analysis
Classifier: Programming Language :: Python :: 3.9
Classifier: Programming Language :: Python :: 3.10
Classifier: Programming Language :: Python :: 3.11
Classifier: License :: OSI Approved :: BSD License
Classifier: Intended Audience :: Science/Research
Classifier: Topic :: Scientific/Engineering
Requires-Python: <3.12,>=3.9
License-File: LICENSE.md
Requires-Dist: packaging>=24.0
Requires-Dist: psutil>=5.7.2
Requires-Dist: coloredlogs>=10.0
Requires-Dist: tabulate>=0.8.9
Requires-Dist: redis>=4.5
Requires-Dist: tqdm>=4.50.2
Requires-Dist: filelock>=3.4.2
Requires-Dist: GitPython<=3.1.43
Requires-Dist: protobuf<=3.20.3
Requires-Dist: jinja2>=3.1.2
Requires-Dist: watchdog<5,>4
Requires-Dist: pydantic>2
Requires-Dist: pyzmq>=25.1.2
Requires-Dist: pygithub>=2.3.0
Requires-Dist: numpy<2
Requires-Dist: smartredis<0.7,>=0.6
Provides-Extra: dev
Requires-Dist: black==24.1a1; extra == "dev"
Requires-Dist: isort>=5.6.4; extra == "dev"
Requires-Dist: pylint<3,>=2.10.0; extra == "dev"
Requires-Dist: pytest>=6.0.0; extra == "dev"
Requires-Dist: pytest-cov>=2.10.1; extra == "dev"
Requires-Dist: click==8.0.2; extra == "dev"
Requires-Dist: pytest-asyncio>=0.23.3; extra == "dev"
Provides-Extra: docs
Requires-Dist: Sphinx==6.2.1; extra == "docs"
Requires-Dist: breathe==4.35.0; extra == "docs"
Requires-Dist: sphinx-fortran==1.1.1; extra == "docs"
Requires-Dist: sphinx-book-theme==1.0.1; extra == "docs"
Requires-Dist: sphinx-copybutton==0.5.2; extra == "docs"
Requires-Dist: sphinx-tabs==3.4.4; extra == "docs"
Requires-Dist: nbsphinx==0.9.3; extra == "docs"
Requires-Dist: docutils==0.18.1; extra == "docs"
Requires-Dist: torch==2.0.1; extra == "docs"
Requires-Dist: tensorflow<3.0,>=2.14; extra == "docs"
Requires-Dist: ipython; extra == "docs"
Requires-Dist: jinja2==3.1.2; extra == "docs"
Requires-Dist: sphinx-design; extra == "docs"
Requires-Dist: pypandoc; extra == "docs"
Requires-Dist: sphinx-autodoc-typehints; extra == "docs"
Requires-Dist: myst-parser; extra == "docs"
Provides-Extra: mypy
Requires-Dist: mypy>=1.3.0; extra == "mypy"
Requires-Dist: types-psutil; extra == "mypy"
Requires-Dist: types-redis; extra == "mypy"
Requires-Dist: types-tabulate; extra == "mypy"
Requires-Dist: types-tqdm; extra == "mypy"
Requires-Dist: types-tensorflow; extra == "mypy"
Requires-Dist: types-setuptools; extra == "mypy"
Requires-Dist: typing-extensions>=4.1.0; extra == "mypy"
